mock_autogen/__init__.py
mock_autogen/ast_tree_travel.py
mock_autogen/generator.py
mock_autogen/pytest_mocker.py
mock_autogen/utils.py
tests/__init__.py
tests/conftest.py
tests/test_ast_tree_travel.py
tests/test_generator.py
tests/test_public_api.py
tests/test_pytest_mocker.py
tests/test_utils.py
tests/sample/__init__.py
tests/sample/code/__init__.py
tests/sample/code/assignments.py
tests/sample/code/comprehensions_and_loops.py
tests/sample/code/lambdas.py
tests/sample/code/same_method_name.py
tests/sample/code/second_module.py
tests/sample/code/subscripts.py
tests/sample/code/tested_module.py
tests/sample/code/with_statements.py
mock_generator-2.4.0.dist-info/LICENSE
mock_generator-2.4.0.dist-info/METADATA
mock_generator-2.4.0.dist-info/WHEEL
mock_generator-2.4.0.dist-info/top_level.txt
mock_generator-2.4.0.dist-info/RECORD
