Metadata-Version: 2.1
Name: mock-generator
Version: 2.4.0
Summary: Generate python mocks and assertions quickly
Home-page: https://github.com/pksol/mock_autogen
Author: Peter Kogan
Author-email: kogan.peter@gmail.com
License: MIT
Platform: UNKNOWN
Classifier: License :: OSI Approved :: MIT License
Classifier: Programming Language :: Python :: 3
Classifier: Programming Language :: Python :: 3.7
Classifier: Programming Language :: Python :: 3.8
Classifier: Programming Language :: Python :: 3.9
Classifier: Programming Language :: Python :: 3.10
Classifier: Operating System :: OS Independent
Requires-Python: >=3.7
Requires-Dist: mock (>=3.0.5)
Requires-Dist: pyperclip (==1.8.2)
